{
  "settings": {
    "_comment": "Change max-token-length to the maximum number of tokens in a sentence",
    "max_token_length": 30
  },
  "intents": [
    {
      "tag": "plugin-get_random_number",
      "patterns": [
        "gib mir eine zufällige zahl",
        "ich hätte gerne eine zufällige zahl",
        "kannst du mir ne random zahl geben",
        "ich hätte gerne ne random zahl",
        "ich hätte gerne eine random zahl",
        "ich hätte gerne eine zufallszahl",
        "gib mir eine random zahl",
        "gib mir eine zufallszahl",
        "gib mal ne random zahl"
      ],
      "responses": [
        "Hier ist deine zufällige Zahl: {number}",
        "Deine zufällige Zahl ist: {number}",
        "Ich habe dir eine zufällige Zahl gegeben: {number}"
      ],
      "action": "plugin-get_random_number-action",
      "error_msg": null
    },
    {
      "tag": "greeting",
      "patterns": [
        "hi",
        "hallo",
        "was geht",
        "wie gehts",
        "hey",
        "moin",
        "guten tag",
        "einen guten tag wünsch ich dir",
        "hello",
        "servus",
        "grüß dich",
        "moin moin",
        "na",
        "hi there",
        "hiho",
        "wasup",
        "whats up"
      ],
      "responses": [
        "Hallo%if_name%, {name}%if_name_end%!",
        "Guten Tag%if_name%, {name}%if_name_end%.",
        "Hallo%if_name%, {name}!%if_name_end%",
        "Guten Tag%if_names%, {name}%if_names_end%."
      ],
      "action": "greet_user",
      "error_msg": null
    },
    {
      "tag": "bye",
      "patterns": [
        "bye",
        "man sieht sich",
        "adios",
        "cya",
        "tschüss",
        "tschau",
        "auf wiedersehen",
        "bis morgen",
        "tschö",
        "machs gut",
        "wir sehen uns",
        "bis bald",
        "auf bald",
        "schönen tag noch",
        "cu",
        "bye bye"
      ],
      "responses": [
        "Man sieht sich!"
      ],
      "action": null,
      "error_msg": null
    },
    {
      "tag": "current_time",
      "patterns": [
        "was zeigt die uhr?",
        "ich brauche die uhrzeit",
        "kannst du mir sagen wie spät es ist",
        "welche tageszeit haben wir gerade",
        "zeit bitte!",
        "sag mir wie viel uhr es ist",
        "ich benötige die uhrzeit",
        "ich möchte wissen wie spät es ist",
        "gib mir die aktuelle zeitangabe",
        "wie spät haben wir",
        "kannst du mir die gegenwärtige uhrzeit verraten",
        "ich hätte gerne die uhrzeit",
        "bitte informiere mich über die aktuelle uhrzeit",
        "zeig mir die uhr",
        "welche zeit ist es jetzt?",
        "ich benötige bitte die uhrzeit",
        "wie viel uhr ist es?",
        "wie viel uhr haben wir gerade?"
      ],
      "responses": [
        "Es ist gerade {hour} Uhr {minutes}.",
        "Die Uhr zeigt {hour} Uhr {minutes} an.",
        "Es ist jetzt {hour} Uhr {minutes}.",
        "Die aktuelle Uhrzeit ist {hour} Uhr {minutes}.",
        "Es ist {hour} Uhr {minutes}.",
        "Es ist aktuel {hour} Uhr {minutes}"
      ],
      "error_msg": "Tut mir leid, ich war nicht in der Lage, die jetzige Uhrzeit zu bekommen.",
      "action": "get_current_time"
    },
    {
      "tag": "play_song",
      "patterns": [
        "spiele bohemian rhapsody von queen auf spotify ab",
        "spiele shape of you von ed sheeran auf youtube ab",
        "spiele den song hotel california von eagles ab",
        "spiele imagine von john lennon bitte auf youtube ab",
        "spiele den hit blinding lights von the weeknd auf spotify ab",
        "spiele despacito von luis fonsi auf youtube ab",
        "spiele den song rolling in the deep von adele ab",
        "spiele thriller von michael jackson auf spotify ab",
        "spiele bohemian rhapsody von queen auf youtube ab",
        "spiele den song yellow von coldplay bitte auf spotify ab",
        "spiele a thousand years von christina perri auf youtube ab",
        "spiele den hit someone like you von adele auf spotify ab",
        "spiele let it be von the beatles auf youtube ab",
        "spiele den song perfect von ed sheeran bitte auf spotify ab",
        "spiele hotel california von eagles auf youtube ab",
        "spiele the scientist von coldplay auf spotify ab",
        "spiele den song all of me von john legend auf youtube ab",
        "spiele imagine von john lennon auf spotify ab",
        "spiele den hit blinding lights von the weeknd auf youtube ab",
        "spiele shape of you von ed sheeran auf spotify ab",
        "spiele despacito von luis fonsi auf spotify ab",
        "spiele bohemian rhapsody von queen auf deezer ab",
        "spiele den song rolling in the deep von adele auf youtube ab",
        "spiele let it be von the beatles bitte auf spotify ab",
        "spiele den song yellow von coldplay auf youtube ab",
        "spiele thriller von michael jackson auf youtube ab",
        "spiele someone like you von adele auf deezer ab",
        "spiele den song perfect von ed sheeran auf youtube ab",
        "spiele hotel california von eagles auf spotify ab",
        "spiele the scientist von coldplay auf youtube ab",
        "spiele den song all of me von john legend auf spotify ab",
        "spiele imagine von john lennon auf deezer ab",
        "spiele a thousand years von christina perri auf spotify ab",
        "spiele bohemian rhapsody von queen auf apple music ab",
        "spiele den hit blinding lights von the weeknd bitte auf spotify ab",
        "spiele shape of you von ed sheeran auf deezer ab",
        "spiele despacito von luis fonsi auf youtube ab",
        "spiele hotel california von eagles bitte auf spotify ab",
        "spiele let it be von the beatles auf deezer ab",
        "spiele den song perfect von ed sheeran auf deezer ab",
        "spiele the scientist von coldplay bitte auf spotify ab",
        "spiele someone like you von adele auf apple music ab",
        "spiele den song all of me von john legend auf deezer ab",
        "spiele thriller von michael jackson auf deezer ab",
        "spiele imagine von john lennon auf apple music ab",
        "spiele a thousand years von christina perri auf deezer ab",
        "spiele bohemian rhapsody von queen bitte auf spotify ab",
        "spiele den hit blinding lights von the weeknd auf deezer ab",
        "spiele shape of you von ed sheeran auf apple music ab",
        "spiele hotel california von eagles auf apple music ab",
        "spiele despacito von luis fonsi bitte auf spotify ab",
        "spiele let it be von the beatles auf apple music ab",
        "spiele den song perfect von ed sheeran bitte auf deezer ab",
        "spiele the scientist von coldplay auf apple music ab",
        "spiele someone like you von adele auf youtube ab",
        "spiele den song all of me von john legend bitte auf spotify ab",
        "spiele thriller von michael jackson bitte auf spotify ab",
        "spiele imagine von john lennon auf amazon music ab",
        "spiele a thousand years von christina perri auf apple music ab",
        "spiele bohemian rhapsody von queen auf amazon music ab",
        "spiele den hit blinding lights von the weeknd auf apple music ab",
        "spiele shape of you von ed sheeran bitte auf deezer ab",
        "spiele hotel california von eagles auf amazon music ab",
        "spiele despacito von luis fonsi auf apple music ab",
        "spiele let it be von the beatles bitte auf deezer ab",
        "spiele den song perfect von ed sheeran auf amazon music ab",
        "spiele the scientist von coldplay auf amazon music ab",
        "spiele someone like you von adele auf spotify ab",
        "spiele den song all of me von john legend auf amazon music ab",
        "spiele thriller von michael jackson auf amazon music ab",
        "spiele imagine von john lennon bitte auf deezer ab",
        "spiele a thousand years von christina perri auf amazon music ab",
        "spiele bohemian rhapsody von queen auf tidal ab",
        "spiele den hit blinding lights von the weeknd bitte auf deezer ab",
        "spiele shape of you von ed sheeran auf amazon music ab",
        "spiele hotel california von eagles auf tidal ab",
        "spiele despacito von luis fonsi bitte auf deezer ab",
        "spiele let it be von the beatles auf tidal ab",
        "spiele den song perfect von ed sheeran auf tidal ab",
        "spiele the scientist von coldplay bitte auf deezer ab",
        "spiele someone like you von adele auf tidal ab",
        "spiele den song all of me von john legend bitte auf deezer ab",
        "spiele thriller von michael jackson bitte auf deezer ab",
        "spiele imagine von john lennon auf tidal ab",
        "spiele a thousand years von christina perri bitte auf deezer ab",
        "spiele bohemian rhapsody von queen auf youtube music ab",
        "spiele den hit blinding lights von the weeknd auf tidal ab",
        "spiele shape of you von ed sheeran bitte auf tidal ab",
        "spiele hotel california von eagles auf youtube music ab",
        "spiele despacito von luis fonsi auf tidal ab",
        "spiele let it be von the beatles auf youtube music ab",
        "spiele den song perfect von ed sheeran bitte auf tidal ab",
        "spiele the scientist von coldplay auf tidal ab",
        "spiele someone like you von adele bitte auf tidal ab",
        "spiele den song all of me von john legend auf tidal ab",
        "spiele thriller von michael jackson auf tidal ab",
        "spiele verstand von absent",
        "spiele den song verstand von absent",
        "spiele den song verstand von absent ab",
        "spiele den song verstand von absent bitte ab",
        "spiele den song verstand ab",
        "spiele den song verstand bitte ab",
        "spiele den song verstand auf youtube ab",
        "spiele den song verstand bitte auf youtube ab",
        "spiele den song verstand von absent auf youtube ab",
        "spiele den song verstand von absent bitte auf youtube ab",
        "spiele verstand von absent auf youtube ab",
        "spiele verstand von absent auf spotify ab",
        "spiele verstand von absent bitte auf spotify ab"
      ],
      "responses": [
        "Okay, ich spiele {song_name} von {artist_name} auf {platform_name} ab.",
        "Das Lied {song_name} von {artist_name} wird jetzt auf {platform_name} abgespielt.",
        "Ich spiele {song_name} von {artist_name} auf {platform_name} ab."
      ],
      "error_msg": "Tut mir leid, beim Abspielen des Songs ist ein Fehler aufgetreten.",
      "action": "play_song"
    },
    {
      "tag": "clear_chat",
      "patterns": [
        "bitte den chat entleeren",
        "kannst du sämtliche nachrichten im chat löschen",
        "ich wünsche mir einen sauberen chat räum ihn auf",
        "bitte alle chateinträge entfernen",
        "bitte den verlauf klären",
        "könntest du den chatinhalt löschen",
        "ich hätte gern einen leeren chat kannst du das tun",
        "der chat ist voll bitte cleare ihn",
        "bitte beseitige den gesamten chatverlauf",
        "kannst du den chatinhalt bitte ausradieren",
        "bitte den chatverlauf zurücksetzen",
        "bitte den chat ausräumen",
        "der chatverlauf ist zu unordentlich lösche ihn bitte",
        "kannst du alle nachrichten im chat auslöschen",
        "bitte sämtliche chateinträge löschen",
        "bitte mach den chat leer",
        "könntest du den chatinhalt entfernen",
        "ich bevorzuge einen sauberen chat bitte mach das",
        "bitte bereinige den chatverlauf",
        "bitte den chatverlauf auswischen",
        "kannst du den chat säubern",
        "bitte den chatinhalt ausradieren",
        "kannst du den chatverlauf auslöschen",
        "bitte den chat entrümpeln",
        "bitte alle nachrichten hier im chat entfernen",
        "ich hätte gerne einen frischen chat reinige ihn",
        "bitte den chat löschen",
        "bitte mach den chatverlauf sauber",
        "bitte den chat clear",
        "bitte leere den chatverlauf",
        "kannst du den chatverlauf entfernen",
        "bitte den gesamten chat löschen",
        "bitte clear den chat",
        "kannst du den chat sauber machen",
        "bitte den chatinhalt löschen",
        "bitte lösche den chatverlauf",
        "bitte leere den chat",
        "bitte den chatinhalt entfernen",
        "könntest du den chat leeren",
        "ich bevorzuge einen sauberen chat lösche ihn bitte",
        "bitte den chatinhalt ausradieren",
        "bitte den chatverlauf löschen"
      ],
      "responses": [
        "Ich habe den Chatverlauf gelöscht.",
        "Der Chatverlauf wurde gelöscht.",
        "Der Chatverlauf ist jetzt leer.",
        "Ich habe den Chatverlauf erfolgreich geleert."
      ],
      "error_msg": "Tut mir leid, ich konnte den Chatverlauf nicht löschen.",
      "action": "clear_chat"
    },
    {
      "tag": "tell_joke",
      "patterns": [
        "erzähl mir einen weiteren witz",
        "kannst du einen witz erzählen",
        "ich möchte gerne lachen",
        "erzähl einen witz",
        "ich will einen witz hören",
        "bitte einen witz",
        "zeig mir deinen besten witz",
        "möchtest du einen witz erzählen",
        "ein witz, bitte",
        "ich brauche etwas zum schmunzeln",
        "kannst du mich zum lachen bringen",
        "ich freue mich auf einen witz",
        "ein humorvoller spruch wäre toll",
        "schenk mir ein lächeln mit einem witz",
        "ich warte auf einen neuen witz",
        "ich möchte lachen, erzähl einen witz",
        "lass mich schmunzeln, erzähl einen witz",
        "gib mir einen witz",
        "ich bin gespannt auf deinen witz",
        "zeig mir, wie lustig du sein kannst",
        "erzähl einen humorvollen spruch",
        "ich könnte einen lacher gebrauchen",
        "ein witz zum aufheitern wäre großartig",
        "ich brauche unterhaltung, erzähl einen witz",
        "ich bin bereit für einen neuen witz",
        "mache mich glücklich, erzähl einen witz",
        "ich wünsche mir einen witz",
        "ich brauche einen guten witz",
        "ich möchte etwas lustiges hören",
        "ich bin in stimmung für einen witz",
        "bitte erzähl einen weiteren witz",
        "kannst du mich mit einem witz amüsieren",
        "ich könnte einen scherz gebrauchen",
        "ein weiterer witz, bitte",
        "ich lache gerne, erzähl einen witz",
        "ich warte auf deinen witzlichen spruch",
        "sorg für ein lächeln mit einem witz",
        "erzähl mir einen weiteren humorvollen witz",
        "ich freue mich auf einen lacher",
        "ich bin gespannt auf deinen humor",
        "kannst du einen witzlichen spruch erzählen",
        "zeig mir, wie witzig du sein kannst",
        "ein humorvoller spruch, bitte",
        "ich lache gerne, erzähl einen witz",
        "kannst du mich mit einem witz amüsieren",
        "ich könnte einen scherz gebrauchen",
        "ein weiterer witz, bitte",
        "ich lache gerne, erzähl einen witz",
        "ich warte auf deinen witzlichen spruch",
        "sorg für ein lächeln mit einem witz",
        "erzähl mir einen weiteren humorvollen witz",
        "ich freue mich auf einen lacher",
        "ich bin gespannt auf deinen humor",
        "kannst du einen witzlichen spruch erzählen",
        "zeig mir, wie witzig du sein kannst",
        "ein humorvoller spruch, bitte",
        "ich lache gerne, erzähl einen witz",
        "kannst du mich mit einem witz amüsieren",
        "ich könnte einen scherz gebrauchen",
        "ein weiterer witz, bitte",
        "ich lache gerne, erzähl einen witz",
        "ich warte auf deinen witzlichen spruch",
        "sorg für ein lächeln mit einem witz",
        "erzähl mir einen weiteren humorvollen witz",
        "ich freue mich auf einen lacher",
        "ich bin gespannt auf deinen humor",
        "kannst du einen witzlichen spruch erzählen",
        "zeig mir, wie witzig du sein kannst",
        "ein humorvoller spruch, bitte",
        "ich lache gerne, erzähl einen witz",
        "kannst du mich mit einem witz amüsieren",
        "ich könnte einen scherz gebrauchen",
        "ein weiterer witz, bitte",
        "ich lache gerne, erzähl einen witz",
        "ich warte auf deinen witzlichen spruch",
        "sorg für ein lächeln mit einem witz",
        "erzähl mir einen weiteren humorvollen witz",
        "ich freue mich auf einen lacher",
        "ich bin gespannt auf deinen humor",
        "kannst du einen witzlichen spruch erzählen",
        "zeig mir, wie witzig du sein kannst",
        "ein humorvoller spruch, bitte",
        "ich lache gerne, erzähl einen witz",
        "kannst du mich mit einem witz amüsieren",
        "ich könnte einen scherz gebrauchen",
        "ein weiterer witz, bitte",
        "ich lache gerne, erzähl einen witz",
        "ich warte auf deinen witzlichen spruch",
        "sorg für ein lächeln mit einem witz",
        "erzähl mir einen weiteren humorvollen witz",
        "ich freue mich auf einen lacher",
        "ich bin gespannt auf deinen humor",
        "kannst du einen witzlichen spruch erzählen",
        "zeig mir, wie witzig du sein kannst",
        "ein humorvoller spruch, bitte",
        "ich lache gerne, erzähl einen witz",
        "erzähl mir nen weiteren witz",
        "kannst du nen witz erzählen",
        "ich möcht gerne lachen",
        "erzähl nen witz",
        "ich will nen witz hören",
        "bitte nen witz",
        "zeig mir deinen besten witz",
        "möchtest du nen witz erzählen",
        "nen witz, bitte",
        "ich brauch was zum schmunzeln",
        "kannst du mich zum lachen bringen",
        "ich freu mich auf nen witz",
        "nen humorvollen spruch wäre toll",
        "schenk mir ein lächeln mit nem witz",
        "ich warte auf nen neuen witz",
        "ich möcht lachen, erzähl nen witz",
        "lass mich schmunzeln, erzähl nen witz",
        "gib mir nen witz",
        "ich bin gespannt auf deinen witz",
        "zeig mir, wie lustig du sein kannst",
        "erzähl nen humorvollen spruch",
        "ich könnt nen lacher gebrauchen",
        "nen witz zum aufheitern wär großartig",
        "ich brauch unterhaltung, erzähl nen witz",
        "ich bin bereit für nen neuen witz",
        "mach mich glücklich, erzähl nen witz",
        "ich wünsch mir nen witz",
        "ich brauch nen guten witz",
        "ich möcht was lustiges hören",
        "ich bin in stimmung für nen witz",
        "bitte erzähl nen weiteren witz",
        "kannst du mich mit nem witz amüsieren",
        "ich könnt nen scherz gebrauchen",
        "nen weiteren witz, bitte",
        "ich lache gern, erzähl nen witz",
        "ich warte auf deinen witzlichen spruch",
        "sorg für ein lächeln mit nem witz",
        "erzähl mir nen weiteren humorvollen witz",
        "ich freu mich auf nen lacher",
        "ich bin gespannt auf deinen humor",
        "kannst du nen witzlichen spruch erzählen",
        "zeig mir, wie witzig du sein kannst",
        "nen humorvollen spruch, bitte",
        "ich lache gern, erzähl nen witz",
        "kannst du mich mit nem witz amüsieren",
        "ich könnt nen scherz gebrauchen",
        "nen weiteren witz, bitte",
        "ich lache gern, erzähl nen witz",
        "ich warte auf deinen witzlichen spruch",
        "sorg für ein lächeln mit nem witz",
        "erzähl mir nen weiteren humorvollen witz",
        "ich freu mich auf nen lacher",
        "ich bin gespannt auf deinen humor",
        "kannst du nen witzlichen spruch erzählen",
        "zeig mir, wie witzig du sein kannst",
        "nen humorvollen spruch, bitte",
        "ich lache gern, erzähl nen witz",
        "kannst du mich mit nem witz amüsieren",
        "ich könnt nen scherz gebrauchen",
        "nen weiteren witz, bitte",
        "ich lache gern, erzähl nen witz",
        "ich warte auf deinen witzlichen spruch",
        "sorg für ein lächeln mit nem witz",
        "erzähl mir nen weiteren humorvollen witz",
        "ich freu mich auf nen lacher",
        "ich bin gespannt auf deinen humor",
        "kannst du nen witzlichen spruch erzählen",
        "zeig mir, wie witzig du sein kannst",
        "nen humorvollen spruch, bitte",
        "ich lache gern, erzähl nen witz",
        "kannst du mich mit nem witz amüsieren",
        "ich könnt nen scherz gebrauchen",
        "nen weiteren witz, bitte",
        "ich lache gern, erzähl nen witz",
        "ich warte auf deinen witzlichen spruch",
        "sorg für ein lächeln mit nem witz",
        "erzähl mir nen weiteren humorvollen witz",
        "ich freu mich auf nen lacher",
        "ich bin gespannt auf deinen humor",
        "kannst du nen witzlichen spruch erzählen",
        "zeig mir, wie witzig du sein kannst",
        "nen humorvollen spruch, bitte",
        "ich lache gern, erzähl nen witz",
        "kannst du mich mit nem witz amüsieren",
        "ich könnt nen scherz gebrauchen",
        "nen weiteren witz, bitte",
        "ich lache gern, erzähl nen witz",
        "ich warte auf deinen witzlichen spruch"
      ],
      "responses": [
        "Hier ist ein Witz:<br><br>{joke}"
      ],
      "error_msg": "Tut mir leid, ich konnte keinen Witz finden.",
      "action": "tell_joke"
    },
    {
      "tag": "again",
      "patterns": [
        "noch mal",
        "nochmal",
        "wiederholen",
        "erneut",
        "noch eins",
        "bitte noch einen",
        "noch eine",
        "noch einen mehr",
        "nochmals",
        "noch weiter",
        "noch einen dazu",
        "einen weiteren bitte",
        "noch eine wiederholung",
        "gerne nochmal",
        "bitte erneut",
        "wiederholung, bitte",
        "noch eine wiederholung, wenn möglich",
        "ich möchte es nochmal hören",
        "bitte noch einen weiteren",
        "eine wiederholung, wenn es geht",
        "nochmal von vorne",
        "wiederhole es, bitte",
        "noch einen versuch",
        "noch eine wiederholung, wenn du möchtest",
        "noch einen obendrauf",
        "ich hätte gern eine wiederholung",
        "noch eine wiederholung dazu",
        "nochmal, wenn es dir nichts ausmacht",
        "bitte nochmal von vorne",
        "wiederhole es, wenn es geht",
        "noch einen versuch, bitte",
        "noch eine wiederholung, wenn es geht",
        "ich möchte es nochmal hören, wenn möglich",
        "noch eine wiederholung, wenn du magst",
        "nochmal von vorne, bitte",
        "noch einen versuch, wenn es dir nichts ausmacht",
        "noch eine wiederholung dazu, bitte",
        "wiederhole es, wenn es dir nichts ausmacht",
        "nochmal von vorne, wenn möglich",
        "noch einen versuch, wenn du möchtest",
        "noch eine wiederholung, wenn du möchtest, bitte",
        "nochmal von vorne, wenn du magst",
        "noch einen versuch, bitte, wenn du möchtest",
        "noch eine wiederholung, wenn du möchtest, bitte"
      ],
      "responses": [
        "{response}"
      ],
      "error_msg": "Tut mir leid, ich habe das nicht verstanden.",
      "action": "repeat"
    },
    {
      "tag": "open_website",
      "patterns": [
        "könnten sie gvnlkokrmecsdfk.ru in internet explorer öffnen",
        "könntest du bitte mdlametnwgbbrfm.ru in firefox öffnen",
        "kannst du bitte takentook.net in opera öffnen",
        "könnten sie srbhsxcnrtxttbe.ru in internet explorer öffnen",
        "kannst du eventuell 2epp6y15m9gv0obj2y1h722o0.org in edge öffnen",
        "öffne bitte lvjibtgcvkhav.ru in dem browser edge",
        "könnten sie syrhjhhbhkwdlhs.ru in internet explorer öffnen",
        "könnten sie xqxkpfvkxtoderotwpqgu.ru in firefox öffnen",
        "kannst du eventuell ktwhmhetkfipkbtfmxucpbkr.ru in firefox öffnen",
        "würden sie nnfvfumcihbolqt.ru in firefox für mich öffnen",
        "bitte öffne ugjqgeykepkycxd.ru",
        "könntest du bitte ngynaorbe.cx in internet explorer öffnen",
        "öffne bitte spotcompe.net in internet explorer",
        "öffne in firefox bitte die domain lpwlnqjbyctrt.ru",
        "öffne bitte cmtqfbajgbjt.ru",
        "kannst du bitte vevawahkqkleely.ru in meinem browser öffnen",
        "öffne arboggqvalhcvlf.ru in edge",
        "öffne bitte vrwphnfjbukgugvxltreh.ga in dem browser edge",
        "öffne in edge bitte die domain lepphiuomejes.tj",
        "öffne in internet explorer bitte die domain btftligsyjfl.ru",
        "bitte öffnen sie in chrome die domain vbunrhkvytflvr.biz",
        "würden sie hkompxterubmlsj.ru in edge für mich öffnen",
        "bitte öffne die domain 187y7v514ehk1oaqndlx1tvkxze.com in edge",
        "würden sie pickboat.net in opera für mich öffnen",
        "öffne cloudrest.net in meinem browser",
        "bitte öffne elrxrbtlvsoxlqx.ug in edge",
        "öffne ftvpodxbwdony.ru in meinem browser",
        "bitte öffne die domain gmirgtulcorj.ru in meinem browser",
        "kannst du eventuell puhoualfthviu.com in edge öffnen",
        "öffne in edge bitte die domain kddtquylrdsf.ru",
        "könnten sie uwrainhpteorafc.eu in opera öffnen",
        "bitte öffne jlyucyvetbwtti.ru in internet explorer",
        "kannst du bitte bgamqvjnqprgaki.ru in internet explorer öffnen",
        "öffne in meinem browser bitte die domain mcolotaantnihxo.ru",
        "öffne bitte rflhdwemsxrqy.ru in dem browser internet explorer",
        "öffne lruehltptnyit.ru in chrome",
        "öffne bitte audkjiwghinvs.ru in dem browser firefox",
        "öffne die website ggceskfxhcgqru.ru",
        "kannst du bitte rvwrnlbhogcuo.ru in firefox öffnen",
        "öffne in chrome bitte die domain kivbhotrlkymrp.ru",
        "bitte öffnen sie in opera die domain jkpjygadgmgtmsq.ru",
        "öffne in meinem browser bitte die domain 4mk9j4s28orogjiecz1d9zv7j.net",
        "kannst du bitte b3a73e664da3d0df9dc2838fd1a254e0.org in opera öffnen",
        "öffne bitte 1p6euix1plmlwb6nnhw31cdcn9x.net in opera",
        "öffne bitte sgqcjjelfayne.in in dem browser opera",
        "bitte öffnen sie miltnaubnmlqax.ru",
        "öffne in chrome bitte die domain k06tig3w0sghhiitp1mqwut9.net",
        "öffne bitte jqkqasltuowicwgni.eu in opera",
        "bitte öffne die domain vkgbqrjpumdtlwx.ru in firefox",
        "kannst du bitte jyfyntmyyvgksghx.mn in firefox öffnen",
        "bitte öffnen sie in opera die domain whomsaturday.net",
        "öffne wnnklutkajppb.ru in internet explorer",
        "bitte öffne die domain ixrrolgpvmqixwv.info in firefox",
        "kannst du eventuell wyrnpjfhrrknvna.co.uk in chrome öffnen",
        "öffne mzo5pm1vn1qo1dsh7wm1tk7q5d.org in firefox",
        "öffne bitte die domain yvrdimbdehat.ru",
        "würden sie 1qxlf5c1epn2yc1sju4sy1bo8941.org in opera für mich öffnen",
        "bitte öffnen sie gnnfmhwumgli.ru",
        "könntest du bitte ilulqotjbpmabl.ru in opera öffnen",
        "bitte öffnen sie in internet explorer die domain tqfqgwmvgm.so",
        "bitte öffne lcnvtbpobwdmkiqnvnio.kz in chrome",
        "öffne in opera bitte die domain xnvnvlwhvvree.ru",
        "öffne die website uponmoon.net",
        "kannst du bitte phyogbuhjqucugo.ru in opera öffnen",
        "öffne in edge bitte die domain qhrzstv67ci31n1g7mmi7hn.net",
        "öffne in internet explorer bitte die domain wajxdigjhvjqkjw.ru",
        "öffne bitte tool9r1c68s4p6cmhlmfxb1dq.net in dem browser meinem browser",
        "kannst du eventuell hgdxnaww.co in chrome öffnen",
        "bitte öffnen sie in edge die domain llmc5wnc3bi7ccha1j147c6f9.biz",
        "könntest du bitte mbuixdjicclhl.com in edge öffnen",
        "öffne in meinem browser bitte die domain ixumutwqsagwv.co.uk",
        "öffne bitte hffkdyvct.bz in dem browser firefox",
        "öffne bitte die domain pwucedzilubz1e5gp2k1s6fk6i.biz",
        "bitte öffnen sie in firefox die domain ymsxymqdlfsa.ru",
        "bitte öffne die domain 1vi6jc2hanvwv4ovdl450wvm4.net in firefox",
        "bitte öffnen sie in firefox die domain afjayhlxyapuxu.ru",
        "bitte öffne die domain pusdxsdvfdxabej.ru in edge",
        "würden sie 8v4flw1pokk5112gz3vk14n6eub.biz in internet explorer für mich öffnen",
        "kannst du eventuell mbdmeododts.la in edge öffnen",
        "öffne bitte qqve0tk2w9o71xn5rwe11vcplb.net in firefox",
        "kannst du bitte 114lf4h184kt4tosa8s74gezt.org in opera öffnen",
        "bitte öffnen sie in chrome die domain 1p4by0k1ye64dp1lh22rqkad4bq.org",
        "öffne in firefox bitte die domain x29bq01vl7m4ztca9sn1smi0um.org",
        "kannst du eventuell yhquodatbetaezdyxdrgxpryx.ru in edge öffnen",
        "öffne yvjjkwftaehqttjdglwfp.pro in firefox",
        "könnten sie obxsowfojbrdrp.ru in chrome öffnen",
        "öffne in meinem browser bitte die domain lbgaqvhjdgdot.ru",
        "würden sie foelerqyfxgg.ru in firefox für mich öffnen",
        "öffne watchhurry.net in chrome",
        "bitte öffne die domain oolurjtkfiwegrq.ru in chrome",
        "öffne bitte tutyuvtnslqnk.org in dem browser firefox",
        "könntest du bitte rcastwt.bit in meinem browser öffnen",
        "öffne fingkomwdfkogwy.ru",
        "öffne sundaybroke.net in meinem browser",
        "bitte öffne 1t3acz11kz5euc1r7dnnz1y5b2jo.com",
        "könnten sie 1bung3h1dqb6ixsbo32q19zhlj.biz in meinem browser öffnen",
        "könnten sie 14cpf8g18vb3f8js7pv21vdm1l.net in meinem browser öffnen",
        "könntest du bitte 1408f8117il2lhi1wvtx1ukfbyu.com in meinem browser öffnen",
        "öffne spendshoe.net in edge",
        "öffne in internet explorer bitte die domain uvkehvhhclcc.ru",
        "könntest du bitte enohnknrvraxyqx.ru in meinem browser öffnen",
        "öffne bitte eftlsvgujbxsq.ru in opera",
        "öffne bitte ydtcberklbmfbqbmhlfdixctcdt.ru",
        "kannst du bitte withnews.net in meinem browser öffnen",
        "würden sie aneaccikhgbyo.ru in opera für mich öffnen",
        "bitte öffne die domain cctbycpikcyrh.ru in internet explorer",
        "öffne uenkjwstmhjnjdm.ru in internet explorer",
        "öffne in edge bitte die domain 1rjwivo7okx9itl2f3f1qcxsm8.net",
        "bitte öffne die domain ahqyeuoriofpq.ru in firefox",
        "kannst du bitte fqjwielik.eu in meinem browser öffnen",
        "öffne in firefox bitte die domain jmuquobnngkbf.biz",
        "öffne bitte dreammarry.net in dem browser internet explorer",
        "öffne bitte lwxekjwjlfrqr.ru in internet explorer",
        "öffne bitte hpavqbsybgjnfn.ru in chrome",
        "bitte öffne die domain casecroud.net in chrome",
        "öffne in chrome bitte die domain ac0a848c1760c5c1b3b4545b5cd5c546.org",
        "könnten sie rjcmefdnvnbde.ru in chrome öffnen",
        "bitte öffnen sie in edge die domain bnolfworpxrred.ru",
        "würden sie pgacbsvvgscm.biz in firefox für mich öffnen",
        "bitte öffne 138bkwonady671duzbyp1qd3n6j.com in firefox",
        "könnten sie lmieeavktgkl.ru in meinem browser öffnen",
        "öffne bitte xcncbpdbuavm.ru in dem browser meinem browser",
        "könntest du bitte bbhiaanlxuymgm.ru in internet explorer öffnen",
        "könnten sie dmwldetiqnbmie.ru in opera öffnen",
        "öffne in meinem browser bitte die domain lftabtaslhwkcbptuvm.me",
        "könntest du bitte 14u31xo1ylsoa0jdsnupzbipqi.biz in edge öffnen",
        "öffne die website fixxoorhmaeaqhmhlntkvwlrug.ru",
        "öffne bitte ii87fsyvseams84ycg1wdwi60.net in internet explorer",
        "öffne in internet explorer bitte die domain qyouxdhthbkny.ru",
        "würden sie yfslxcrrbyvtxwshqbd.mx in meinem browser für mich öffnen",
        "könntest du bitte avppqdrydjit.ru in opera öffnen",
        "könntest du bitte 1yqhnw288n74v1gxs2k31o199j4.com in internet explorer öffnen",
        "könnten sie cmxhscofifdyeyukdcmrwnjhpz.ru in meinem browser öffnen",
        "kannst du bitte 1nduwqh1lih9m0jtsbgw19u4a4o.net in firefox öffnen",
        "öffne bitte upaehtjumopsa.net in dem browser firefox",
        "bitte öffnen sie in meinem browser die domain 509272ff119d8a7d465e6de951dd44af.org",
        "könntest du bitte wishsure.net in internet explorer öffnen",
        "öffne bitte obkjsvsirdfle.info in chrome",
        "öffne bitte feltvoice.net in meinem browser",
        "öffne niifjstbijvx.ru in internet explorer",
        "bitte öffnen sie die domain lseyybtvyyqga.ru",
        "bitte öffnen sie in internet explorer die domain pvpnugbumfzdxwclozxcpnrcqgskjb.ru",
        "öffne bitte gfydtmxutupal.org in chrome",
        "öffne bitte oyrfhuaollqwkcicto.kz in dem browser opera",
        "öffne in meinem browser bitte die domain nivolviybpckyb.ru",
        "bitte öffne die domain 3bh99za7pahg121y8r61wp662z.com in edge",
        "öffne in opera bitte die domain mmhmgjapnkvbh.ru",
        "bitte öffne die domain ytrtbtkvwsmpufm.biz in opera",
        "kannst du eventuell takenthem.net in internet explorer öffnen",
        "könnten sie cloudshade.net in meinem browser öffnen",
        "öffne in opera bitte die domain 1qylwrm5nebawy79bxh1y0ysp8.net",
        "könnten sie cloudthirteen.net in chrome öffnen",
        "bitte öffnen sie in firefox die domain nakrqjoejqvu.ru",
        "könntest du bitte bao8l7197w7bj1vgicc81e7spem.com in chrome öffnen",
        "würden sie jhoa3z1w9xowledtfr4ignvul.net in firefox für mich öffnen",
        "kannst du eventuell jdlfjnfeqtnna.ru in chrome öffnen",
        "bitte öffnen sie in opera die domain hgwnkxgaduyah.ru",
        "könnten sie xyskn71999typ175h6tggeyfde.biz in firefox öffnen",
        "kannst du bitte axdvprtyhbkuca.ru in opera öffnen",
        "könntest du bitte grwvk41io6ur7t685sm1u95tqf.net in chrome öffnen",
        "kannst du eventuell mskntdhccduscy.ru in chrome öffnen",
        "öffne bitte feltpaid.net in dem browser chrome",
        "öffne 1jjarmr1c09y7stv9jmy1433hn0.org in edge",
        "kannst du eventuell unrkyivwqsqi.ru in meinem browser öffnen",
        "bitte öffne die domain 1p8gjvgcd0yqb1ou6hkj1ilorm1.com in firefox",
        "öffne bitte dbirnfhvrgatjvg.ru",
        "bitte öffne die domain evjkgjtmyiwi.sx in firefox",
        "öffne bitte eyhwcgyfhhyudb.ir in chrome",
        "könntest du bitte lwwkmisinadcjt.ru in internet explorer öffnen",
        "kannst du bitte oseqhboiodmaw.mx in edge öffnen",
        "kannst du eventuell wrongworld.net in firefox öffnen",
        "bitte öffne ddxskljtgdguzingylrp.ru in chrome",
        "würden sie ableneck.net in opera für mich öffnen",
        "öffne bitte wfrmefdu.de in internet explorer",
        "öffne in chrome bitte die domain wmanlwtpyiser.ru",
        "öffne in edge bitte die domain ebfdyefmmoih.ru",
        "könntest du bitte ugjirvpsidmi.ms in edge öffnen",
        "kannst du eventuell dddtlmikjekq.ru in meinem browser öffnen",
        "würden sie pickwing.net in internet explorer für mich öffnen",
        "öffne gwcpfvagdbkejn.info in edge",
        "würden sie southfebruary.net in chrome für mich öffnen",
        "öffne in chrome bitte die domain skofwceytchlrkpzyhfyrhq.ru",
        "bitte öffne die domain nxctvqvdmcknate.ru in chrome",
        "öffne in chrome bitte die domain rtisnhywnqlv.ru",
        "könntest du bitte wnfkrttpfvamnw.co.uk in firefox öffnen",
        "würden sie qxiixqvdbmwomujqj.us in firefox für mich öffnen",
        "öffne bitte 1r185xsk2jj1q1wwr9sm1lwb1vz.org in firefox",
        "öffne die website aafc5w1qdj5ru1je1tmqegg0ol.biz",
        "öffne bitte die domain xvffdwxfvwdn.ru",
        "bitte öffnen sie in opera die domain 21601aa6f4fdf00938765ea532381ae1.org",
        "könnten sie mjxwpcofhqzvozdljscjfzpp.ru in edge öffnen",
        "öffne in chrome bitte die domain pgxuhhhpjxrooay.ru",
        "bitte öffne die domain ysjfyxxoudsxn.ru in internet explorer",
        "könnten sie mcetcvrrjrhna.com in meinem browser öffnen",
        "könntest du bitte ymklbjckaxff.ru in edge öffnen",
        "bitte öffne awnirvekikhc.biz in meinem browser",
        "könnten sie wcsdwvdbpimqg.ru in opera öffnen",
        "könntest du bitte rfbkvswbftwdcgm.ru in edge öffnen",
        "öffne in opera bitte die domain aglpebmfkrfx.biz",
        "bitte öffne die domain 1002ra86698fjpgqke1cdvbk5.org in internet explorer",
        "öffne bitte cunyjmgerpkiww.ru in edge"
      ],
      "responses": [
        "Ich habe die Seite {website} geöffnet.",
        "Die Seite {website} wurde geöffnet.",
        "Ich habe die Seite {website} für sie geöffnet."
      ],
      "error_msg": "Tut mir leid, ich konnte die Seite nicht öffnen.",
      "action": "open_website"
    },
    {
      "tag": "stopword",
      "patterns": [
        "a",
        "ab",
        "aber",
        "ach",
        "acht",
        "achte",
        "achten",
        "achter",
        "achtes",
        "ag",
        "alle",
        "allein",
        "allem",
        "allen",
        "aller",
        "allerdings",
        "alles",
        "allgemeinen",
        "als",
        "also",
        "am",
        "an",
        "ander",
        "andere",
        "anderem",
        "anderen",
        "anderer",
        "anderes",
        "anderm",
        "andern",
        "anderr",
        "anders",
        "au",
        "auch",
        "auf",
        "aus",
        "ausser",
        "ausserdem",
        "außer",
        "außerdem",
        "b",
        "bald",
        "bei",
        "beide",
        "beiden",
        "beim",
        "beispiel",
        "bekannt",
        "bereits",
        "besonders",
        "besser",
        "besten",
        "bin",
        "bis",
        "bisher",
        "bist",
        "c",
        "d",
        "d.h",
        "da",
        "dabei",
        "dadurch",
        "dafür",
        "dagegen",
        "daher",
        "dahin",
        "dahinter",
        "damals",
        "damit",
        "danach",
        "daneben",
        "dank",
        "dann",
        "daran",
        "darauf",
        "daraus",
        "darf",
        "darfst",
        "darin",
        "darum",
        "darunter",
        "darüber",
        "das",
        "dasein",
        "daselbst",
        "dass",
        "dasselbe",
        "davon",
        "davor",
        "dazu",
        "dazwischen",
        "daß",
        "dein",
        "deine",
        "deinem",
        "deinen",
        "deiner",
        "deines",
        "dem",
        "dementsprechend",
        "demgegenüber",
        "demgemäss",
        "demgemäß",
        "demselben",
        "demzufolge",
        "den",
        "denen",
        "denn",
        "denselben",
        "der",
        "deren",
        "derer",
        "derjenige",
        "derjenigen",
        "dermassen",
        "dermaßen",
        "derselbe",
        "derselben",
        "des",
        "deshalb",
        "desselben",
        "dessen",
        "deswegen",
        "dich",
        "die",
        "diejenige",
        "diejenigen",
        "dies",
        "diese",
        "dieselbe",
        "dieselben",
        "diesem",
        "diesen",
        "dieser",
        "dieses",
        "dir",
        "doch",
        "dort",
        "drei",
        "drin",
        "dritte",
        "dritten",
        "dritter",
        "drittes",
        "du",
        "durch",
        "durchaus",
        "durfte",
        "durften",
        "dürfen",
        "dürft",
        "e",
        "eben",
        "ebenso",
        "ehrlich",
        "ei",
        "ei,",
        "eigen",
        "eigene",
        "eigenen",
        "eigener",
        "eigenes",
        "ein",
        "einander",
        "eine",
        "einem",
        "einen",
        "einer",
        "eines",
        "einig",
        "einige",
        "einigem",
        "einigen",
        "einiger",
        "einiges",
        "einmal",
        "eins",
        "elf",
        "en",
        "ende",
        "endlich",
        "entweder",
        "er",
        "ernst",
        "erst",
        "erste",
        "ersten",
        "erster",
        "erstes",
        "es",
        "etwa",
        "etwas",
        "euch",
        "euer",
        "eure",
        "eurem",
        "euren",
        "eurer",
        "eures",
        "f",
        "folgende",
        "früher",
        "fünf",
        "fünfte",
        "fünften",
        "fünfter",
        "fünftes",
        "für",
        "g",
        "gab",
        "ganz",
        "ganze",
        "ganzen",
        "ganzer",
        "ganzes",
        "gar",
        "gedurft",
        "gegen",
        "gegenüber",
        "gehabt",
        "gehen",
        "geht",
        "gekannt",
        "gekonnt",
        "gemacht",
        "gemocht",
        "gemusst",
        "genug",
        "gerade",
        "gern",
        "gesagt",
        "geschweige",
        "gewesen",
        "gewollt",
        "geworden",
        "gibt",
        "ging",
        "gleich",
        "gott",
        "gross",
        "grosse",
        "grossen",
        "grosser",
        "grosses",
        "groß",
        "große",
        "großen",
        "großer",
        "großes",
        "gut",
        "gute",
        "guter",
        "gutes",
        "h",
        "hab",
        "habe",
        "haben",
        "habt",
        "hast",
        "hat",
        "hatte",
        "hatten",
        "hattest",
        "hattet",
        "heisst",
        "her",
        "heute",
        "hier",
        "hin",
        "hinter",
        "hoch",
        "hätte",
        "hätten",
        "i",
        "ich",
        "ihm",
        "ihn",
        "ihnen",
        "ihr",
        "ihre",
        "ihrem",
        "ihren",
        "ihrer",
        "ihres",
        "im",
        "immer",
        "in",
        "indem",
        "infolgedessen",
        "ins",
        "irgend",
        "ist",
        "j",
        "ja",
        "jahr",
        "jahre",
        "jahren",
        "je",
        "jede",
        "jedem",
        "jeden",
        "jeder",
        "jedermann",
        "jedermanns",
        "jedes",
        "jedoch",
        "jemand",
        "jemandem",
        "jemanden",
        "jene",
        "jenem",
        "jenen",
        "jener",
        "jenes",
        "jetzt",
        "k",
        "kam",
        "kann",
        "kannst",
        "kaum",
        "kein",
        "keine",
        "keinem",
        "keinen",
        "keiner",
        "keines",
        "kleine",
        "kleinen",
        "kleiner",
        "kleines",
        "kommen",
        "kommt",
        "konnte",
        "konnten",
        "kurz",
        "können",
        "könnt",
        "könnte",
        "l",
        "lang",
        "lange",
        "leicht",
        "leide",
        "lieber",
        "los",
        "m",
        "machen",
        "macht",
        "machte",
        "mag",
        "magst",
        "mahn",
        "mal",
        "man",
        "manche",
        "manchem",
        "manchen",
        "mancher",
        "manches",
        "mann",
        "mehr",
        "mein",
        "meine",
        "meinem",
        "meinen",
        "meiner",
        "meines",
        "mensch",
        "menschen",
        "mich",
        "mir",
        "mit",
        "mittel",
        "mochte",
        "mochten",
        "morgen",
        "muss",
        "musst",
        "musste",
        "mussten",
        "muß",
        "mußt",
        "möchte",
        "mögen",
        "möglich",
        "mögt",
        "müssen",
        "müsst",
        "müßt",
        "n",
        "na",
        "nach",
        "nachdem",
        "nahm",
        "natürlich",
        "neben",
        "nein",
        "neue",
        "neuen",
        "neun",
        "neunte",
        "neunten",
        "neunter",
        "neuntes",
        "nicht",
        "nichts",
        "nie",
        "niemand",
        "niemandem",
        "niemanden",
        "noch",
        "nun",
        "nur",
        "o",
        "ob",
        "oben",
        "oder",
        "offen",
        "oft",
        "ohne",
        "ordnung",
        "p",
        "q",
        "r",
        "recht",
        "rechte",
        "rechten",
        "rechter",
        "rechtes",
        "richtig",
        "rund",
        "s",
        "sa",
        "sache",
        "sagt",
        "sagte",
        "sah",
        "satt",
        "schlecht",
        "schluss",
        "schon",
        "sechs",
        "sechste",
        "sechsten",
        "sechster",
        "sechstes",
        "sehr",
        "sei",
        "seid",
        "seien",
        "sein",
        "seine",
        "seinem",
        "seinen",
        "seiner",
        "seines",
        "seit",
        "seitdem",
        "selbst",
        "sich",
        "sie",
        "sieben",
        "siebente",
        "siebenten",
        "siebenter",
        "siebentes",
        "sind",
        "so",
        "solang",
        "solche",
        "solchem",
        "solchen",
        "solcher",
        "solches",
        "soll",
        "sollen",
        "sollst",
        "sollt",
        "sollte",
        "sollten",
        "sondern",
        "sonst",
        "soweit",
        "sowie",
        "später",
        "startseite",
        "statt",
        "steht",
        "suche",
        "t",
        "tag",
        "tage",
        "tagen",
        "tat",
        "teil",
        "tel",
        "tritt",
        "trotzdem",
        "tun",
        "u",
        "uhr",
        "um",
        "und",
        "uns",
        "unse",
        "unsem",
        "unsen",
        "unser",
        "unsere",
        "unserer",
        "unses",
        "unter",
        "v",
        "vergangenen",
        "viel",
        "viele",
        "vielem",
        "vielen",
        "vielleicht",
        "vier",
        "vierte",
        "vierten",
        "vierter",
        "viertes",
        "vom",
        "von",
        "vor",
        "w",
        "wahr",
        "wann",
        "war",
        "waren",
        "warst",
        "wart",
        "warum",
        "was",
        "weg",
        "wegen",
        "weil",
        "weit",
        "weiter",
        "weitere",
        "weiteren",
        "weiteres",
        "welche",
        "welchem",
        "welchen",
        "welcher",
        "welches",
        "wem",
        "wen",
        "wenig",
        "wenige",
        "weniger",
        "weniges",
        "wenigstens",
        "wenn",
        "wer",
        "werde",
        "werden",
        "werdet",
        "weshalb",
        "wessen",
        "wie",
        "wieder",
        "wieso",
        "will",
        "willst",
        "wir",
        "wird",
        "wirklich",
        "wirst",
        "wissen",
        "wo",
        "woher",
        "wohin",
        "wohl",
        "wollen",
        "wollt",
        "wollte",
        "wollten",
        "worden",
        "wurde",
        "wurden",
        "während",
        "währenddem",
        "währenddessen",
        "wäre",
        "würde",
        "würden",
        "x",
        "y",
        "z",
        "z.b",
        "zehn",
        "zehnte",
        "zehnten",
        "zehnter",
        "zehntes",
        "zeit",
        "zu",
        "zuerst",
        "zugleich",
        "zum",
        "zunächst",
        "zur",
        "zurück",
        "zusammen",
        "zwanzig",
        "zwar",
        "zwei",
        "zweite",
        "zweiten",
        "zweiter",
        "zweites",
        "zwischen",
        "zwölf",
        "über",
        "überhaupt",
        "übrigens"
      ],
      "responses": [
        "stopword"
      ],
      "action": "stopword-detected",
      "error_msg": null
    }
  ]
}